{
  "hash": "1a23a9ec",
  "configHash": "695e304d",
  "lockfileHash": "ed4f20e4",
  "browserHash": "c0907e30",
  "optimized": {
    "vue": {
      "src": "../../node_modules/vue/dist/vue.runtime.esm-bundler.js",
      "file": "vue.js",
      "fileHash": "36a70730",
      "needsInterop": false
    },
    "vue-router": {
      "src": "../../node_modules/vue-router/dist/vue-router.mjs",
      "file": "vue-router.js",
      "fileHash": "6e77fe0d",
      "needsInterop": false
    }
  },
  "chunks": {
    "chunk-IJV5NOMV": {
      "file": "chunk-IJV5NOMV.js"
    }
  }
}